helloworld.py
bhawick.helloworld-0.0.7.dist-info/LICENSE.txt
bhawick.helloworld-0.0.7.dist-info/METADATA
bhawick.helloworld-0.0.7.dist-info/WHEEL
bhawick.helloworld-0.0.7.dist-info/top_level.txt
bhawick.helloworld-0.0.7.dist-info/RECORD
